LICENSE
MANIFEST.in
README.md
setup.cfg
setup.py
rchain_keygen/__init__.py
rchain_keygen/__main__.py
rchain_keygen/app.py
rchain_keygen/arguments.py
rchain_keygen.egg-info/PKG-INFO
rchain_keygen.egg-info/SOURCES.txt
rchain_keygen.egg-info/dependency_links.txt
rchain_keygen.egg-info/entry_points.txt
rchain_keygen.egg-info/top_level.txt